investimentos/__init__.py
investimentos/investimentos.py
meu_investimento_test-0.1.2.dist-info/licenses/LICENSE
meu_investimento_test-0.1.2.dist-info/METADATA
meu_investimento_test-0.1.2.dist-info/WHEEL
meu_investimento_test-0.1.2.dist-info/top_level.txt
meu_investimento_test-0.1.2.dist-info/RECORD
