Metadata-Version: 2.4
Name: meu_investimento_test
Version: 0.1.2
Summary: Uma biblioteca para cálculos de investimentos.
Home-page: https://github.com/tadrianonet/meu_investimento
Author: Vinicius S. de Oliveira
Author-email: vin.s.oliveira@icloud.com
Classifier: Programming Language :: Python :: 3
Classifier: License :: OSI Approved :: MIT License
Classifier: Operating System :: OS Independent
Requires-Python: >=3.6
License-File: LICENSE
Dynamic: author
Dynamic: author-email
Dynamic: classifier
Dynamic: description
Dynamic: description-content-type
Dynamic: home-page
Dynamic: license-file
Dynamic: requires-python
Dynamic: summary
